dataskillhub/__init__.py
dataskillhub/consultant.py
dataskillhub/cv.py
dataskillhub/extract.py
dataskillhub/init_src.py
dataskillhub/main.py
dataskillhub/assets/cert_psm.svg
dataskillhub/assets/cert_tableau.png
dataskillhub/assets/cert_talend.png
dataskillhub/assets/icon_chat.png
dataskillhub/assets/icon_diploma.png
dataskillhub/assets/icon_person.png
dataskillhub/assets/icon_skill.png
dataskillhub/assets/icon_star.png
dataskillhub/assets/logo.png
dataskillhub/assets/logo_datalyo.png
dataskillhub/assets/style.css
dataskillhub/config/anonyme.json
dataskillhub/config/sections.yml
dataskillhub/templates/index.html
test/__init__.py
test/test_extract.py
dataskillhub-1.7.0.dist-info/METADATA
dataskillhub-1.7.0.dist-info/WHEEL
dataskillhub-1.7.0.dist-info/entry_points.txt
dataskillhub-1.7.0.dist-info/top_level.txt
dataskillhub-1.7.0.dist-info/RECORD
