Metadata-Version: 2.1
Name: dataskillhub
Version: 1.7.0
Summary: Anonymisation et filtrage des termes dans le CV, décoration et style des CV produits.
Home-page: https://gitlab-datalyo.francecentral.cloudapp.azure.com/dossier-de-comp-tences/dossiercompetence
Author: Xin Yao
Author-email: xin.yao@datalyo.com
License: UNKNOWN
Platform: UNKNOWN
Requires-Dist: click (==8.1.7)
Requires-Dist: pydantic (==2.6.3)
Requires-Dist: PyYAML (==6.0.1)
Requires-Dist: Markdown (==3.5.2)
Requires-Dist: weasyprint (==52.5)
Requires-Dist: Jinja2 (==3.1.3)
Requires-Dist: flake8 (==7.0.0)
Requires-Dist: black (==24.2.0)
Requires-Dist: pytest (==8.0.2)
